spinecore/__init__.py
spinecore/common/__init__.py
spinecore/common/context/__init__.py
spinecore/common/context/base_context.py
spinecore/common/context/pandas_context.py
spinecore/common/context/polars_context.py
spinecore/common/context/spark_context.py
spinecore/common/helpers/__init__.py
spinecore/common/helpers/graphs.py
spinecore/common/helpers/contract/IContext.py
spinecore/common/helpers/contract/IExecutor.py
spinecore/common/helpers/contract/IStep.py
spinecore/common/helpers/contract/Logger.py
spinecore/common/helpers/contract/Workflow.py
spinecore/common/helpers/contract/__init__.py
spinecore/common/helpers/contract/metaclasses/__init__.py
spinecore/common/helpers/contract/metaclasses/singleton.py
spinecore/common/helpers/dataframes/__init__.py
spinecore/common/helpers/dataframes/pandas_dataframe.py
spinecore/common/helpers/dataframes/polars_dataframe.py
spinecore/common/helpers/dataframes/spark_dataframe.py
spinecore/common/helpers/logging/__init__.py
spinecore/common/helpers/logging/spine_logger.py
spinecore/common/helpers/steps/__init__.py
spinecore/common/helpers/steps/pandas_step.py
spinecore/common/helpers/steps/polars_step.py
spinecore/common/helpers/steps/spark_step.py
spinecore/executors/__init__.py
spinecore/executors/spine_executor.py
spinecore/executors/workflow_executors/__init__.py
spinecore/executors/workflow_executors/async_workflow_executor.py
spinecore/workflows/__init__.py
spinecore/workflows/dag_workflow.py
spinecore-0.0.20.dist-info/METADATA
spinecore-0.0.20.dist-info/WHEEL
spinecore-0.0.20.dist-info/licenses/LICENSE
spinecore-0.0.20.dist-info/RECORD
