Metadata-Version: 2.1
Name: spinecore
Version: 0.0.20
Summary: The core lib of spine library
Project-URL: Homepage, https://github.com/shaharluftig/spine
Author-email: Shahar Luftig <shaharluftig@gmail.com>
License:                                  Apache License
License-File: LICENSE
Keywords: core,dag,data enginnering,data pipline,dataframe,spine,workflow
Classifier: Intended Audience :: Science/Research
Classifier: Operating System :: OS Independent
Classifier: Programming Language :: Python
Classifier: Programming Language :: Python :: 3
Classifier: Programming Language :: Python :: 3 :: Only
Classifier: Programming Language :: Python :: 3.7
Classifier: Programming Language :: Python :: 3.8
Classifier: Programming Language :: Python :: 3.9
Classifier: Programming Language :: Python :: 3.10
Classifier: Programming Language :: Python :: 3.11
Classifier: Topic :: Scientific/Engineering
Requires-Python: >=3.7
Requires-Dist: matplotlib~=3.7.1
Requires-Dist: networkx~=3.0
Requires-Dist: stringcase~=1.2.0
Provides-Extra: all
Requires-Dist: spinecore[pandas]; extra == 'all'
Requires-Dist: spinecore[polars]; extra == 'all'
Requires-Dist: spinecore[spark]; extra == 'all'
Provides-Extra: pandas
Requires-Dist: pandas~=2.0.0; extra == 'pandas'
Provides-Extra: polars
Requires-Dist: connectorx~=0.3.2a2; extra == 'polars'
Requires-Dist: polars~=0.20.2; extra == 'polars'
Requires-Dist: pyarrow~=14.0.1; extra == 'polars'
Provides-Extra: spark
Requires-Dist: pyspark~=3.2.1; extra == 'spark'
